{
  "sprint": "Sprint1002",
  "task": "FixItFred_Complete_Error_Warning_Sweep",
  "timestamp": "2025-08-02T02:45:00Z",
  "summary": {
    "initial_errors": 1096,
    "final_errors": 42,
    "errors_resolved": 1054,
    "warnings_initial": 1,
    "warnings_final": 1,
    "success_rate": "96.2%"
  },
  "files_changed": [
    "GlobalUsings.cs - Fixed namespace references to match actual project structure",
    "Data/Models/Seo.cs - Removed duplicate Seo class definition",
    "Data/ApplicationDbContext.cs - Fixed model references and ambiguous types",
    "Program.cs - Fixed namespace references and added missing DI registrations",
    "FixItFred/Extensions/Diagnostics/FixItFredDiagnostics.cs - Added implementation",
    "Multiple Razor files - Fixed @model directives to use correct namespaces",
    "Multiple .cs files - Fixed MVP_Core.* namespace references",
    "Created missing models: UserContext, JobMetaData, ReportComparison"
  ],
  "major_fixes": [
    "Removed duplicate class definitions (Seo, RecoveryAILearningService)",
    "Fixed all MVP_Core namespace references to correct format",
    "Created missing model classes referenced in DbContext",
    "Fixed GlobalUsings.cs to only reference existing namespaces",
    "Fixed _ViewImports.cshtml files across the project",
    "Resolved ambiguous type references with explicit qualification",
    "Fixed AutoRepairEngine DI registration",
    "Added missing BackgroundService using statement"
  ],
  "remaining_issues": [
    "42 compilation errors remain, mostly related to:",
    "- Pages.Services.Admin namespace resolution in some files",
    "- Auto-generated Razor files expecting different namespace format",
    "- Missing page model classes for some Razor files"
  ],
  "obsolete_services": [
    {
      "service": "ValidationSimulatorService",
      "status": "Marked with [Obsolete] attribute",
      "location": "Services/Admin/ValidationSimulatorService.cs"
    }
  ],
  "comments_added": {
    "fixitfred_comments": "Added to all modified files with Sprint1002 tag",
    "reasoning": "Documented exact reason for each modification"
  },
  "test_coverage_impact": "Not applicable - no test files modified",
  "build_status": "PARTIAL_SUCCESS",
  "validation_results": {
    "dotnet_clean": "SUCCESS",
    "dotnet_build": "PARTIAL_SUCCESS - 42 errors remaining",
    "zero_errors_achieved": false,
    "zero_warnings_achieved": false
  },
  "next_steps": [
    "Resolve remaining 42 compilation errors",
    "Add null checks and retry logic to SignalR hubs",
    "Apply RazorLayoutSyncRule to all Razor files",
    "Validate Services and ViewModels with public accessors",
    "Run associated test suites"
  ]
}